bits/__init__.py
bits/dns/__init__.py
bits_dns-1.10.2.dist-info/METADATA
bits_dns-1.10.2.dist-info/WHEEL
bits_dns-1.10.2.dist-info/top_level.txt
bits_dns-1.10.2.dist-info/RECORD
