Metadata-Version: 2.1
Name: bits-dns
Version: 1.10.2
Summary: BITS DNS
Home-page: UNKNOWN
Author: Lukas Karlsson
Author-email: karlsson@broadinstitute.org
License: Apache Software License
Platform: UNKNOWN
Requires-Dist: pyyaml
